Metadata-Version: 1.1
Name: javasaur
Version: 0.1.1
Summary: Pure python library for Java code analysis
Home-page: https://github.com/tstreamDOTh/javasaur
Author: Thiyagaraj T
Author-email: tstream.h@outlook.com
License: UNKNOWN
Download-URL: https://github.com/tstreamDOTh/javasaur/archive/0.1.1.tar.gz
Keywords: java,javalang,javaparser,parser
Platform: UNKNOWN
